<?xml version='1.0'?>
<southAmerica>
    <country>
        <Name>Argentina</Name>
        <currency>Argentinian Pesos</currency>
        <city>Buenos Aires
                <airfare>€750</airfare>
                <busfare>€15</busfare>
                <zooticket>€18</zooticket>
        </city>
            <city>Bariloche
                <airfare>€750</airfare>
                <busfare>€15</busfare>
                <zooticket>€18</zooticket>
        </city>
          <city>Cordoba
                <airfare>€750</airfare>
                <busfare>€15</busfare>
                <zooticket>€18</zooticket>
        </city>
    </country>
    <country>
        <Name>Bolivia</Name>
        <currency>Boliviano</currency>
            <city>La Paz
                <airfare>€750</airfare>
                <busfare>€15</busfare>
                <zooticket>€18</zooticket>
            </city>
            <city>Cochabamba
                <airfare>€750</airfare>
                <busfare>€15</busfare>
                <zooticket>€18</zooticket>
            </city>
            <city>Oruro
                <airfare>€850</airfare>
                <busfare>€10</busfare>
                <zooticket>€13</zooticket>
            </city>
     </country>
   <country>
        <Name>Brasil</Name>
        <currency>Brazilian Reais</currency>
            <city>Brasilia
                <airfare>€850</airfare>
                <busfare>€10</busfare>
                <zooticket>€13</zooticket>
            </city>
            <city>Fortaleza
                <airfare>€850</airfare>
                <busfare>€10</busfare>
                <zooticket>€13</zooticket>
            </city>
            <city>Rio de Janeiro
                <airfare>€680</airfare>
                <busfare>€20</busfare>
                <zooticket>€15</zooticket>
            </city>
    </country>
 <country>
        <Name>Uruguay</Name>
        <currency>Uruguayan Peso</currency>
            <city>Montevideo
                <airfare>€680</airfare>
                <busfare>€20</busfare>
                <zooticket>€15</zooticket>
            </city>
            <city>Salto
                <airfare>€680</airfare>
                <busfare>€20</busfare>
                <zooticket>€15</zooticket>
            </city>
            <city>Cuidad de la Costa
                <airfare>€680</airfare>
                <busfare>€20</busfare>
                <zooticket>€15</zooticket>
            </city>
    </country>
 <country>
        <Name>Peru</Name>
        <currency>Sol</currency>
            <city>Lima
                <airfare>€450</airfare>
                <busfare>€12</busfare>
                <zooticket>€10</zooticket> 
            </city> 
            <city>Cuzco
                <airfare>€450</airfare>
                <busfare>€12</busfare>
                <zooticket>€10</zooticket> 
            </city> 
            <city>Aguas Verdes
                <airfare>€450</airfare>
                <busfare>€12</busfare>
                <zooticket>€10</zooticket>
            </city> 
    </country>
 <country>
        <Name>Chile</Name>
        <currency>Chilean Peso</currency>
            <city>Santiago
                <airfare>€800</airfare>
                <busfare>€20</busfare>
                <zooticket>€20</zooticket>
            </city>
            <city>Vina del Mar
                <airfare>€800</airfare>
                <busfare>€20</busfare>
                <zooticket>€20</zooticket>
            </city>
            <city>Temuco
                <airfare>€800</airfare>
                <busfare>€20</busfare>
                <zooticket>€20</zooticket>
            </city>
    </country>
  <country>
        <Name>Colombia</Name>
        <currency>Peso Colombiano</currency>
            <city>Bogota
                <airfare>€900</airfare>
                <busfare>€15</busfare>
                <zooticket>€12</zooticket>
            </city>
            <city>Medellin
                <airfare>€900</airfare>
                <busfare>€15</busfare>
                <zooticket>€12</zooticket>
            </city>
            <city>Pereira
                <airfare>€900</airfare>
                <busfare>€15</busfare>
                <zooticket>€12</zooticket> 
            </city> 
    </country>
  <country>
        <Name>Ecuador</Name>
        <currency>Dolar</currency>
            <city>Quito
                <airfare>€900</airfare>
                <busfare>€15</busfare>
                <zooticket>€12</zooticket>
            </city>
            <city>Guayaquil
                <airfare>€900</airfare>
                <busfare>€15</busfare>
                <zooticket>€12</zooticket>
            </city>
            <city>Cuenca
                <airfare>€900</airfare>
                <busfare>€15</busfare>
                <zooticket>€12</zooticket>
            </city>
    </country>
  <country>
        <Name>Venezuela</Name>
        <currency>Bolivar</currency>
            <city>Caracas
                <airfare>€950</airfare>
                <busfare>€20</busfare>
                <zooticket>€25</zooticket>
            </city>
            <city>Maracaibo
                <airfare>€950</airfare>
                <busfare>€20</busfare>
                <zooticket>€25</zooticket>
            </city>
            <city>Valencia
                <airfare>€950</airfare>
                <busfare>€20</busfare>
                <zooticket>€25</zooticket>
            </city>
    </country>
  <country>
        <Name>Guyana</Name>
        <currency>Dolar Guyanes</currency>
            <city>Georgetown
                <airfare>€950</airfare>
                <busfare>€20</busfare>
                <zooticket>€25</zooticket>
            </city>
            <city>Linden
                <airfare>€950</airfare>
                <busfare>€20</busfare>
                <zooticket>€25</zooticket>
            </city>
            <city>Mahaica
                <airfare>€950</airfare>
                <busfare>€20</busfare>
                <zooticket>€25</zooticket>
            </city>
    </country>
  <country>
        <Name>Surinam</Name>
        <currency>Dolar Surinames</currency>
            <city>Paramaribo
                <airfare>€1,200</airfare>
                <busfare>€30</busfare>
                <zooticket>€25</zooticket>
            </city>
            <city>Leydorp
                <airfare>€1,200</airfare>
                <busfare>€30</busfare>
                <zooticket>€25</zooticket>
            </city>
            <city>Moengo
                <airfare>€1,200</airfare>
                <busfare>€30</busfare>
                <zooticket>€25</zooticket>
            </city>
    </country>
  <country>
        <Name>Paraguay</Name>
        <currency>Guarani</currency>
            <city>Asuncion
                <airfare>€1,300</airfare>
                <busfare>€25</busfare>
                <zooticket>€25</zooticket>
            </city>
            <city>Cuidad del Este
                <airfare>€1,300</airfare>
                <busfare>€25</busfare>
                <zooticket>€25</zooticket>
            </city>
            <city>Luque
                <airfare>€1,300</airfare>
                <busfare>€25</busfare>
                <zooticket>€25</zooticket>
            </city>
    </country>
  <country>
        <Name>Belice</Name>
        <currency>Dolar</currency>
            <city>Belmopan
                <airfare>€750</airfare>
                <busfare>€15</busfare>
                <zooticket>€15</zooticket>
            </city>
            <city>Corozal
                <airfare>€750</airfare>
                <busfare>€15</busfare>
                <zooticket>€15</zooticket>
            </city>
            <city>Dangiga
                <airfare>€750</airfare>
                <busfare>€15</busfare>
                <zooticket>€15</zooticket>
            </city>
    </country>
  <country>
        <Name>Costa Rica</Name>
        <currency>Colon</currency>
            <city>San Jose
                <airfare>€670</airfare>
                <busfare>€20</busfare>
                <zooticket>€15</zooticket>
            </city>
            <city>Paraiso
                <airfare>€670</airfare>
                <busfare>€20</busfare>
                <zooticket>€15</zooticket>
            </city>
            <city>Puntarenas
                <airfare>€670</airfare>
                <busfare>€20</busfare>
                <zooticket>€15</zooticket>
            </city>
    </country>
  <country>
        <Name>El Salvador</Name>
        <currency>Dolar USD</currency>
            <city>San Salvador
                <airfare>€700</airfare>
                <busfare>€12</busfare>
                <zooticket>€15</zooticket>
            </city>
            <city>Mejicanos
                <airfare>€700</airfare>
                <busfare>€12</busfare>
                <zooticket>€15</zooticket>
            </city>
            <city>Apopa
                <airfare>€700</airfare>
                <busfare>€12</busfare>
                <zooticket>€15</zooticket>
            </city>
    </country>
  <country>
        <Name>Guatemala</Name>
        <currency>Quetzal GTQ</currency>
            <city>Guatemala
                <airfare>€800</airfare>
                <busfare>€15</busfare>
                <zooticket>€12</zooticket>
            </city>
            <city>Peten
                <airfare>€800</airfare>
                <busfare>€15</busfare>
                <zooticket>€12</zooticket>
            </city>
            <city>Solola
                <airfare>€800</airfare>
                <busfare>€15</busfare>
                <zooticket>€12</zooticket>
            </city>
    </country>
  <country>
        <Name>Nicaragua</Name>
        <currency>Cordoba NIO</currency>
            <city>Managua
                <airfare>€860</airfare>
                <busfare>€25</busfare>
                <zooticket>€18</zooticket>
            </city>
            <city>Leon
                <airfare>€860</airfare>
                <busfare>€25</busfare>
                <zooticket>€18</zooticket>
            </city>
            <city>Granada
                <airfare>€860</airfare>
                <busfare>€25</busfare>
                <zooticket>€18</zooticket>
            </city>
    </country>
  <country>
        <Name>Panama</Name>
        <currency>Dolar</currency>
            <city>Panama
                <airfare>€790</airfare>
                <busfare>€20</busfare>
                <zooticket>€18</zooticket>
            </city>
            <city>Colon
                <airfare>€790</airfare>
                <busfare>€20</busfare>
                <zooticket>€18</zooticket>
            </city>
            <city>Herrera
                <airfare>€790</airfare>
                <busfare>€20</busfare>
                <zooticket>€18</zooticket>
            </city>
    </country>
</southAmerica>
